courier/__init__.py
courier/_base_client.py
courier/_client.py
courier/_compat.py
courier/_constants.py
courier/_exceptions.py
courier/_files.py
courier/_models.py
courier/_qs.py
courier/_resource.py
courier/_response.py
courier/_streaming.py
courier/_types.py
courier/_version.py
courier/py.typed
courier/_utils/__init__.py
courier/_utils/_compat.py
courier/_utils/_datetime_parse.py
courier/_utils/_logs.py
courier/_utils/_proxy.py
courier/_utils/_reflection.py
courier/_utils/_resources_proxy.py
courier/_utils/_streams.py
courier/_utils/_sync.py
courier/_utils/_transform.py
courier/_utils/_typing.py
courier/_utils/_utils.py
courier/lib/.keep
courier/resources/__init__.py
courier/resources/audiences.py
courier/resources/audit_events.py
courier/resources/auth.py
courier/resources/brands.py
courier/resources/bulk.py
courier/resources/inbound.py
courier/resources/messages.py
courier/resources/requests.py
courier/resources/send.py
courier/resources/translations.py
courier/resources/automations/__init__.py
courier/resources/automations/automations.py
courier/resources/automations/invoke.py
courier/resources/lists/__init__.py
courier/resources/lists/lists.py
courier/resources/lists/subscriptions.py
courier/resources/notifications/__init__.py
courier/resources/notifications/checks.py
courier/resources/notifications/draft.py
courier/resources/notifications/notifications.py
courier/resources/profiles/__init__.py
courier/resources/profiles/lists.py
courier/resources/profiles/profiles.py
courier/resources/tenants/__init__.py
courier/resources/tenants/templates.py
courier/resources/tenants/tenants.py
courier/resources/tenants/preferences/__init__.py
courier/resources/tenants/preferences/items.py
courier/resources/tenants/preferences/preferences.py
courier/resources/users/__init__.py
courier/resources/users/preferences.py
courier/resources/users/tenants.py
courier/resources/users/tokens.py
courier/resources/users/users.py
courier/types/__init__.py
courier/types/audience.py
trycourier-7.4.0.dist-info/METADATA
trycourier-7.4.0.dist-info/WHEEL
trycourier-7.4.0.dist-info/licenses/LICENSE
trycourier-7.4.0.dist-info/RECORD
